luffa/__init__.py
luffa-0.0.0.dist-info/WHEEL
luffa-0.0.0.dist-info/METADATA
luffa-0.0.0.dist-info/RECORD
