Metadata-Version: 2.1
Name: luffa
Version: 0.0.0
Summary: Luffa.io command line client
Home-page: UNKNOWN
License: UNKNOWN
Author: Hadrien David
Author-email: hadrien@ectobal.com
Requires-Python: >=3.7,<4.0
Classifier: Programming Language :: Python :: 3
Classifier: Programming Language :: Python :: 3.7
